certifi.py
syscertifi-0.2.dist-info/DESCRIPTION.rst
syscertifi-0.2.dist-info/METADATA
syscertifi-0.2.dist-info/RECORD
syscertifi-0.2.dist-info/WHEEL
syscertifi-0.2.dist-info/metadata.json
syscertifi-0.2.dist-info/top_level.txt
