Metadata-Version: 2.0
Name: syscertifi
Version: 0.2
Summary: Make requests use system certificate stores
Home-page: https://github.com/nanonyme/syscertifi
Author: Seppo Yli-Olli
Author-email: seppo.yli-olli+pypi@iki.fi
License: UNKNOWN
Platform: UNKNOWN
Requires-Dist: wincertstore; sys_platform=='win32'
